[
  {
    "example": "tsp-opt",
    "config": "full",
    "run": 1,
    "baseline": 592.71,
    "final_score": 493.37,
    "delta_pct": 16.76030436469775,
    "backtracks": 1,
    "elapsed": 561.9937281608582,
    "status": "ok",
    "error": ""
  },
  {
    "example": "tsp-opt",
    "config": "full",
    "run": 2,
    "baseline": 592.71,
    "final_score": 497.66,
    "delta_pct": 16.036510266403468,
    "backtracks": 1,
    "elapsed": 566.5315515995026,
    "status": "ok",
    "error": ""
  },
  {
    "example": "tsp-opt",
    "config": "full",
    "run": 3,
    "baseline": 592.71,
    "final_score": 493.37,
    "delta_pct": 16.76030436469775,
    "backtracks": 0,
    "elapsed": 1038.622162103653,
    "status": "ok",
    "error": ""
  },
  {
    "example": "tsp-opt",
    "config": "no_backtrack",
    "run": 1,
    "baseline": 592.71,
    "final_score": 493.37,
    "delta_pct": 16.76030436469775,
    "backtracks": 0,
    "elapsed": 861.7425472736359,
    "status": "ok",
    "error": ""
  },
  {
    "example": "tsp-opt",
    "config": "no_backtrack",
    "run": 2,
    "baseline": 592.71,
    "final_score": 502.36,
    "delta_pct": 15.243542373167319,
    "backtracks": 0,
    "elapsed": 826.5701479911804,
    "status": "ok",
    "error": ""
  },
  {
    "example": "tsp-opt",
    "config": "no_backtrack",
    "run": 3,
    "baseline": 592.71,
    "final_score": 496.91,
    "delta_pct": 16.163047696175195,
    "backtracks": 0,
    "elapsed": 1459.7465908527374,
    "status": "ok",
    "error": ""
  },
  {
    "example": "tsp-opt",
    "config": "single_agent",
    "run": 1,
    "baseline": 592.71,
    "final_score": 496.13,
    "delta_pct": 16.294646623137794,
    "backtracks": 1,
    "elapsed": 181.51388025283813,
    "status": "ok",
    "error": ""
  },
  {
    "example": "tsp-opt",
    "config": "single_agent",
    "run": 2,
    "baseline": 592.71,
    "final_score": 495.35,
    "delta_pct": 16.426245550100386,
    "backtracks": 0,
    "elapsed": 268.7797508239746,
    "status": "ok",
    "error": ""
  },
  {
    "example": "tsp-opt",
    "config": "single_agent",
    "run": 3,
    "baseline": 592.71,
    "final_score": 495.35,
    "delta_pct": 16.426245550100386,
    "backtracks": 0,
    "elapsed": 442.95238161087036,
    "status": "ok",
    "error": ""
  },
  {
    "example": "game-ai",
    "config": "full",
    "run": 1,
    "baseline": 25.62,
    "final_score": 75.0,
    "delta_pct": 192.74004683840747,
    "backtracks": 1,
    "elapsed": 1615.6287877559662,
    "status": "ok",
    "error": ""
  },
  {
    "example": "game-ai",
    "config": "full",
    "run": 2,
    "baseline": 25.62,
    "final_score": 100.0,
    "delta_pct": 290.32006245121,
    "backtracks": 0,
    "elapsed": 2029.127207994461,
    "status": "ok",
    "error": ""
  },
  {
    "example": "game-ai",
    "config": "full",
    "run": 3,
    "baseline": 25.62,
    "final_score": 100.0,
    "delta_pct": 290.32006245121,
    "backtracks": 0,
    "elapsed": 1260.716914176941,
    "status": "ok",
    "error": ""
  },
  {
    "example": "game-ai",
    "config": "no_backtrack",
    "run": 1,
    "baseline": 25.62,
    "final_score": 73.75,
    "delta_pct": 187.86104605776734,
    "backtracks": 0,
    "elapsed": 1694.7981095314026,
    "status": "ok",
    "error": ""
  },
  {
    "example": "game-ai",
    "config": "no_backtrack",
    "run": 2,
    "baseline": 25.62,
    "final_score": 73.75,
    "delta_pct": 187.86104605776734,
    "backtracks": 0,
    "elapsed": 877.6562983989716,
    "status": "ok",
    "error": ""
  },
  {
    "example": "game-ai",
    "config": "no_backtrack",
    "run": 3,
    "baseline": 25.62,
    "final_score": 75.0,
    "delta_pct": 192.74004683840747,
    "backtracks": 0,
    "elapsed": 1277.3481359481812,
    "status": "ok",
    "error": ""
  },
  {
    "example": "game-ai",
    "config": "single_agent",
    "run": 1,
    "baseline": 25.62,
    "final_score": 75.0,
    "delta_pct": 192.74004683840747,
    "backtracks": 0,
    "elapsed": 350.1558129787445,
    "status": "ok",
    "error": ""
  },
  {
    "example": "game-ai",
    "config": "single_agent",
    "run": 2,
    "baseline": 25.62,
    "final_score": 71.88,
    "delta_pct": 180.5620608899297,
    "backtracks": 0,
    "elapsed": 377.0983736515045,
    "status": "ok",
    "error": ""
  },
  {
    "example": "game-ai",
    "config": "single_agent",
    "run": 3,
    "baseline": 25.62,
    "final_score": 86.25,
    "delta_pct": 236.65105386416857,
    "backtracks": 0,
    "elapsed": 712.4906833171844,
    "status": "ok",
    "error": ""
  },
  {
    "example": "bio-opt",
    "config": "full",
    "run": 1,
    "baseline": 39.58,
    "final_score": 42.78,
    "delta_pct": 8.084891359272367,
    "backtracks": 1,
    "elapsed": 773.4648740291595,
    "status": "ok",
    "error": ""
  },
  {
    "example": "bio-opt",
    "config": "full",
    "run": 2,
    "baseline": 39.58,
    "final_score": 54.03,
    "delta_pct": 36.50833754421426,
    "backtracks": 0,
    "elapsed": 1146.3621323108673,
    "status": "ok",
    "error": ""
  },
  {
    "example": "bio-opt",
    "config": "full",
    "run": 3,
    "baseline": 39.58,
    "final_score": 52.92,
    "delta_pct": 33.70389085396666,
    "backtracks": 1,
    "elapsed": 643.5165967941284,
    "status": "ok",
    "error": ""
  },
  {
    "example": "bio-opt",
    "config": "no_backtrack",
    "run": 1,
    "baseline": 39.58,
    "final_score": 39.86,
    "delta_pct": 0.7074279939363344,
    "backtracks": 0,
    "elapsed": 987.1237065792084,
    "status": "ok",
    "error": ""
  },
  {
    "example": "bio-opt",
    "config": "no_backtrack",
    "run": 2,
    "baseline": 39.58,
    "final_score": 44.44,
    "delta_pct": 12.278928751894895,
    "backtracks": 0,
    "elapsed": 845.2442650794983,
    "status": "ok",
    "error": ""
  },
  {
    "example": "bio-opt",
    "config": "no_backtrack",
    "run": 3,
    "baseline": 39.58,
    "final_score": 51.67,
    "delta_pct": 30.545730166750896,
    "backtracks": 0,
    "elapsed": 1069.6996047496796,
    "status": "ok",
    "error": ""
  },
  {
    "example": "bio-opt",
    "config": "single_agent",
    "run": 1,
    "baseline": 39.58,
    "final_score": 39.58,
    "delta_pct": 0.0,
    "backtracks": 0,
    "elapsed": 290.31547951698303,
    "status": "ok",
    "error": ""
  },
  {
    "example": "bio-opt",
    "config": "single_agent",
    "run": 2,
    "baseline": 39.58,
    "final_score": 44.58,
    "delta_pct": 12.632642748863063,
    "backtracks": 1,
    "elapsed": 280.96792364120483,
    "status": "ok",
    "error": ""
  },
  {
    "example": "bio-opt",
    "config": "single_agent",
    "run": 3,
    "baseline": 39.58,
    "final_score": 45.56,
    "delta_pct": 15.108640727640232,
    "backtracks": 1,
    "elapsed": 254.91170024871826,
    "status": "ok",
    "error": ""
  }
]